{
  "db_name": "PostgreSQL",
  "query": "\n    SELECT id as \"id!\", username, password_hash, is_admin as \"is_admin: bool\", is_private as \"is_private: bool\", created_at as \"created_at!\"\n    FROM users\n    WHERE id = $1\n    ",
  "describe": {
    "columns": [
      {
        "ordinal": 0,
        "name": "id!",
        "type_info": "Int8"
      },
      {
        "ordinal": 1,
        "name": "username",
        "type_info": "Text"
      },
      {
        "ordinal": 2,
        "name": "password_hash",
        "type_info": "Text"
      },
      {
        "ordinal": 3,
        "name": "is_admin: bool",
        "type_info": "Bool"
      },
      {
        "ordinal": 4,
        "name": "is_private: bool",
        "type_info": "Bool"
      },
      {
        "ordinal": 5,
        "name": "created_at!",
        "type_info": "Int8"
      }
    ],
    "parameters": {
      "Left": [
        "Int8"
      ]
    },
    "nullable": [
      false,
      false,
      false,
      false,
      false,
      false
    ]
  },
  "hash": "1792873a5c8bbcd9ceaf7a0f9b9b862d3eedcbe2b31c56a3e085454e1a615d13"
}
